{"loss": 0.7098268688234508, "accuracy": 47.43589743589743, "f1_score": 0.0, "time_this_iter_s": 34.9041793346405, "done": false, "timesteps_total": null, "episodes_total": null, "training_iteration": 1, "trial_id": "757a3_00022", "experiment_id": "f424d4f9f37246a9b46ab407a5b0b6b9", "date": "2022-11-16_22-03-31", "timestamp": 1668625411, "time_total_s": 34.9041793346405, "pid": 20244, "hostname": "DESKTOP-G9R02TV", "node_ip": "127.0.0.1", "config": {"learning_rate": 1e-07, "batch_size": 8, "model": "vgg16"}, "time_since_restore": 34.9041793346405, "timesteps_since_restore": 0, "iterations_since_restore": 1, "warmup_time": 0.0}
{"loss": 0.7103264963524973, "accuracy": 47.43589743589743, "f1_score": 0.0, "time_this_iter_s": 31.993800163269043, "done": false, "timesteps_total": null, "episodes_total": null, "training_iteration": 2, "trial_id": "757a3_00022", "experiment_id": "f424d4f9f37246a9b46ab407a5b0b6b9", "date": "2022-11-16_22-04-03", "timestamp": 1668625443, "time_total_s": 66.89797949790955, "pid": 20244, "hostname": "DESKTOP-G9R02TV", "node_ip": "127.0.0.1", "config": {"learning_rate": 1e-07, "batch_size": 8, "model": "vgg16"}, "time_since_restore": 66.89797949790955, "timesteps_since_restore": 0, "iterations_since_restore": 2, "warmup_time": 0.0}
{"loss": 0.7043403560279781, "accuracy": 47.43589743589743, "f1_score": 0.0, "time_this_iter_s": 32.024309396743774, "done": false, "timesteps_total": null, "episodes_total": null, "training_iteration": 3, "trial_id": "757a3_00022", "experiment_id": "f424d4f9f37246a9b46ab407a5b0b6b9", "date": "2022-11-16_22-04-35", "timestamp": 1668625475, "time_total_s": 98.92228889465332, "pid": 20244, "hostname": "DESKTOP-G9R02TV", "node_ip": "127.0.0.1", "config": {"learning_rate": 1e-07, "batch_size": 8, "model": "vgg16"}, "time_since_restore": 98.92228889465332, "timesteps_since_restore": 0, "iterations_since_restore": 3, "warmup_time": 0.0}
{"loss": 0.7113113403320312, "accuracy": 47.43589743589743, "f1_score": 0.0, "time_this_iter_s": 31.82132077217102, "done": false, "timesteps_total": null, "episodes_total": null, "training_iteration": 4, "trial_id": "757a3_00022", "experiment_id": "f424d4f9f37246a9b46ab407a5b0b6b9", "date": "2022-11-16_22-05-07", "timestamp": 1668625507, "time_total_s": 130.74360966682434, "pid": 20244, "hostname": "DESKTOP-G9R02TV", "node_ip": "127.0.0.1", "config": {"learning_rate": 1e-07, "batch_size": 8, "model": "vgg16"}, "time_since_restore": 130.74360966682434, "timesteps_since_restore": 0, "iterations_since_restore": 4, "warmup_time": 0.0}
{"loss": 0.7100564027443911, "accuracy": 47.43589743589743, "f1_score": 0.0, "time_this_iter_s": 32.01524209976196, "done": false, "timesteps_total": null, "episodes_total": null, "training_iteration": 5, "trial_id": "757a3_00022", "experiment_id": "f424d4f9f37246a9b46ab407a5b0b6b9", "date": "2022-11-16_22-05-39", "timestamp": 1668625539, "time_total_s": 162.7588517665863, "pid": 20244, "hostname": "DESKTOP-G9R02TV", "node_ip": "127.0.0.1", "config": {"learning_rate": 1e-07, "batch_size": 8, "model": "vgg16"}, "time_since_restore": 162.7588517665863, "timesteps_since_restore": 0, "iterations_since_restore": 5, "warmup_time": 0.0}
{"loss": 0.7133321517553085, "accuracy": 47.43589743589743, "f1_score": 0.0, "time_this_iter_s": 32.08690643310547, "done": false, "timesteps_total": null, "episodes_total": null, "training_iteration": 6, "trial_id": "757a3_00022", "experiment_id": "f424d4f9f37246a9b46ab407a5b0b6b9", "date": "2022-11-16_22-06-11", "timestamp": 1668625571, "time_total_s": 194.84575819969177, "pid": 20244, "hostname": "DESKTOP-G9R02TV", "node_ip": "127.0.0.1", "config": {"learning_rate": 1e-07, "batch_size": 8, "model": "vgg16"}, "time_since_restore": 194.84575819969177, "timesteps_since_restore": 0, "iterations_since_restore": 6, "warmup_time": 0.0}
{"loss": 0.7017953334710537, "accuracy": 47.43589743589743, "f1_score": 0.0, "time_this_iter_s": 31.898775577545166, "done": false, "timesteps_total": null, "episodes_total": null, "training_iteration": 7, "trial_id": "757a3_00022", "experiment_id": "f424d4f9f37246a9b46ab407a5b0b6b9", "date": "2022-11-16_22-06-43", "timestamp": 1668625603, "time_total_s": 226.74453377723694, "pid": 20244, "hostname": "DESKTOP-G9R02TV", "node_ip": "127.0.0.1", "config": {"learning_rate": 1e-07, "batch_size": 8, "model": "vgg16"}, "time_since_restore": 226.74453377723694, "timesteps_since_restore": 0, "iterations_since_restore": 7, "warmup_time": 0.0}
{"loss": 0.7129748743823451, "accuracy": 47.43589743589743, "f1_score": 0.0, "time_this_iter_s": 31.970520496368408, "done": false, "timesteps_total": null, "episodes_total": null, "training_iteration": 8, "trial_id": "757a3_00022", "experiment_id": "f424d4f9f37246a9b46ab407a5b0b6b9", "date": "2022-11-16_22-07-15", "timestamp": 1668625635, "time_total_s": 258.71505427360535, "pid": 20244, "hostname": "DESKTOP-G9R02TV", "node_ip": "127.0.0.1", "config": {"learning_rate": 1e-07, "batch_size": 8, "model": "vgg16"}, "time_since_restore": 258.71505427360535, "timesteps_since_restore": 0, "iterations_since_restore": 8, "warmup_time": 0.0}
{"loss": 0.7097434671516092, "accuracy": 47.43589743589743, "f1_score": 0.0, "time_this_iter_s": 31.935884952545166, "done": false, "timesteps_total": null, "episodes_total": null, "training_iteration": 9, "trial_id": "757a3_00022", "experiment_id": "f424d4f9f37246a9b46ab407a5b0b6b9", "date": "2022-11-16_22-07-47", "timestamp": 1668625667, "time_total_s": 290.6509392261505, "pid": 20244, "hostname": "DESKTOP-G9R02TV", "node_ip": "127.0.0.1", "config": {"learning_rate": 1e-07, "batch_size": 8, "model": "vgg16"}, "time_since_restore": 290.6509392261505, "timesteps_since_restore": 0, "iterations_since_restore": 9, "warmup_time": 0.0}
{"loss": 0.7202811607947717, "accuracy": 47.43589743589743, "f1_score": 0.0, "time_this_iter_s": 32.05564737319946, "done": false, "timesteps_total": null, "episodes_total": null, "training_iteration": 10, "trial_id": "757a3_00022", "experiment_id": "f424d4f9f37246a9b46ab407a5b0b6b9", "date": "2022-11-16_22-08-19", "timestamp": 1668625699, "time_total_s": 322.70658659935, "pid": 20244, "hostname": "DESKTOP-G9R02TV", "node_ip": "127.0.0.1", "config": {"learning_rate": 1e-07, "batch_size": 8, "model": "vgg16"}, "time_since_restore": 322.70658659935, "timesteps_since_restore": 0, "iterations_since_restore": 10, "warmup_time": 0.0}
{"loss": 0.7059024908603766, "accuracy": 47.43589743589743, "f1_score": 0.0, "time_this_iter_s": 32.02444291114807, "done": false, "timesteps_total": null, "episodes_total": null, "training_iteration": 11, "trial_id": "757a3_00022", "experiment_id": "f424d4f9f37246a9b46ab407a5b0b6b9", "date": "2022-11-16_22-08-51", "timestamp": 1668625731, "time_total_s": 354.73102951049805, "pid": 20244, "hostname": "DESKTOP-G9R02TV", "node_ip": "127.0.0.1", "config": {"learning_rate": 1e-07, "batch_size": 8, "model": "vgg16"}, "time_since_restore": 354.73102951049805, "timesteps_since_restore": 0, "iterations_since_restore": 11, "warmup_time": 0.0}
{"loss": 0.7067691118289263, "accuracy": 47.43589743589743, "f1_score": 0.0, "time_this_iter_s": 32.055328130722046, "done": false, "timesteps_total": null, "episodes_total": null, "training_iteration": 12, "trial_id": "757a3_00022", "experiment_id": "f424d4f9f37246a9b46ab407a5b0b6b9", "date": "2022-11-16_22-09-23", "timestamp": 1668625763, "time_total_s": 386.7863576412201, "pid": 20244, "hostname": "DESKTOP-G9R02TV", "node_ip": "127.0.0.1", "config": {"learning_rate": 1e-07, "batch_size": 8, "model": "vgg16"}, "time_since_restore": 386.7863576412201, "timesteps_since_restore": 0, "iterations_since_restore": 12, "warmup_time": 0.0}
{"loss": 0.7112629556248331, "accuracy": 47.43589743589743, "f1_score": 0.0, "time_this_iter_s": 32.05632519721985, "done": false, "timesteps_total": null, "episodes_total": null, "training_iteration": 13, "trial_id": "757a3_00022", "experiment_id": "f424d4f9f37246a9b46ab407a5b0b6b9", "date": "2022-11-16_22-09-55", "timestamp": 1668625795, "time_total_s": 418.84268283843994, "pid": 20244, "hostname": "DESKTOP-G9R02TV", "node_ip": "127.0.0.1", "config": {"learning_rate": 1e-07, "batch_size": 8, "model": "vgg16"}, "time_since_restore": 418.84268283843994, "timesteps_since_restore": 0, "iterations_since_restore": 13, "warmup_time": 0.0}
{"loss": 0.710062010675414, "accuracy": 47.43589743589743, "f1_score": 0.0, "time_this_iter_s": 31.961289882659912, "done": false, "timesteps_total": null, "episodes_total": null, "training_iteration": 14, "trial_id": "757a3_00022", "experiment_id": "f424d4f9f37246a9b46ab407a5b0b6b9", "date": "2022-11-16_22-10-27", "timestamp": 1668625827, "time_total_s": 450.80397272109985, "pid": 20244, "hostname": "DESKTOP-G9R02TV", "node_ip": "127.0.0.1", "config": {"learning_rate": 1e-07, "batch_size": 8, "model": "vgg16"}, "time_since_restore": 450.80397272109985, "timesteps_since_restore": 0, "iterations_since_restore": 14, "warmup_time": 0.0}
{"loss": 0.7081444243080596, "accuracy": 47.43589743589743, "f1_score": 0.0, "time_this_iter_s": 31.96126413345337, "done": false, "timesteps_total": null, "episodes_total": null, "training_iteration": 15, "trial_id": "757a3_00022", "experiment_id": "f424d4f9f37246a9b46ab407a5b0b6b9", "date": "2022-11-16_22-10-59", "timestamp": 1668625859, "time_total_s": 482.7652368545532, "pid": 20244, "hostname": "DESKTOP-G9R02TV", "node_ip": "127.0.0.1", "config": {"learning_rate": 1e-07, "batch_size": 8, "model": "vgg16"}, "time_since_restore": 482.7652368545532, "timesteps_since_restore": 0, "iterations_since_restore": 15, "warmup_time": 0.0}
{"loss": 0.7124515761677016, "accuracy": 47.43589743589743, "f1_score": 0.0, "time_this_iter_s": 32.278040647506714, "done": false, "timesteps_total": null, "episodes_total": null, "training_iteration": 16, "trial_id": "757a3_00022", "experiment_id": "f424d4f9f37246a9b46ab407a5b0b6b9", "date": "2022-11-16_22-11-31", "timestamp": 1668625891, "time_total_s": 515.0432775020599, "pid": 20244, "hostname": "DESKTOP-G9R02TV", "node_ip": "127.0.0.1", "config": {"learning_rate": 1e-07, "batch_size": 8, "model": "vgg16"}, "time_since_restore": 515.0432775020599, "timesteps_since_restore": 0, "iterations_since_restore": 16, "warmup_time": 0.0}
{"loss": 0.7082509097889957, "accuracy": 47.43589743589743, "f1_score": 0.0, "time_this_iter_s": 32.36804938316345, "done": false, "timesteps_total": null, "episodes_total": null, "training_iteration": 17, "trial_id": "757a3_00022", "experiment_id": "f424d4f9f37246a9b46ab407a5b0b6b9", "date": "2022-11-16_22-12-04", "timestamp": 1668625924, "time_total_s": 547.4113268852234, "pid": 20244, "hostname": "DESKTOP-G9R02TV", "node_ip": "127.0.0.1", "config": {"learning_rate": 1e-07, "batch_size": 8, "model": "vgg16"}, "time_since_restore": 547.4113268852234, "timesteps_since_restore": 0, "iterations_since_restore": 17, "warmup_time": 0.0}
{"loss": 0.7136220035389957, "accuracy": 47.43589743589743, "f1_score": 0.0, "time_this_iter_s": 31.923539400100708, "done": false, "timesteps_total": null, "episodes_total": null, "training_iteration": 18, "trial_id": "757a3_00022", "experiment_id": "f424d4f9f37246a9b46ab407a5b0b6b9", "date": "2022-11-16_22-12-36", "timestamp": 1668625956, "time_total_s": 579.3348662853241, "pid": 20244, "hostname": "DESKTOP-G9R02TV", "node_ip": "127.0.0.1", "config": {"learning_rate": 1e-07, "batch_size": 8, "model": "vgg16"}, "time_since_restore": 579.3348662853241, "timesteps_since_restore": 0, "iterations_since_restore": 18, "warmup_time": 0.0}
{"loss": 0.7098541259765625, "accuracy": 47.008547008547005, "f1_score": 0.0, "time_this_iter_s": 32.10452127456665, "done": false, "timesteps_total": null, "episodes_total": null, "training_iteration": 19, "trial_id": "757a3_00022", "experiment_id": "f424d4f9f37246a9b46ab407a5b0b6b9", "date": "2022-11-16_22-13-08", "timestamp": 1668625988, "time_total_s": 611.4393875598907, "pid": 20244, "hostname": "DESKTOP-G9R02TV", "node_ip": "127.0.0.1", "config": {"learning_rate": 1e-07, "batch_size": 8, "model": "vgg16"}, "time_since_restore": 611.4393875598907, "timesteps_since_restore": 0, "iterations_since_restore": 19, "warmup_time": 0.0}
{"loss": 0.7131450033595419, "accuracy": 47.43589743589743, "f1_score": 0.0, "time_this_iter_s": 32.470011711120605, "done": false, "timesteps_total": null, "episodes_total": null, "training_iteration": 20, "trial_id": "757a3_00022", "experiment_id": "f424d4f9f37246a9b46ab407a5b0b6b9", "date": "2022-11-16_22-13-40", "timestamp": 1668626020, "time_total_s": 643.9093992710114, "pid": 20244, "hostname": "DESKTOP-G9R02TV", "node_ip": "127.0.0.1", "config": {"learning_rate": 1e-07, "batch_size": 8, "model": "vgg16"}, "time_since_restore": 643.9093992710114, "timesteps_since_restore": 0, "iterations_since_restore": 20, "warmup_time": 0.0}
{"loss": 0.7169343997270633, "accuracy": 47.43589743589743, "f1_score": 0.0, "time_this_iter_s": 32.1020143032074, "done": false, "timesteps_total": null, "episodes_total": null, "training_iteration": 21, "trial_id": "757a3_00022", "experiment_id": "f424d4f9f37246a9b46ab407a5b0b6b9", "date": "2022-11-16_22-14-12", "timestamp": 1668626052, "time_total_s": 676.0114135742188, "pid": 20244, "hostname": "DESKTOP-G9R02TV", "node_ip": "127.0.0.1", "config": {"learning_rate": 1e-07, "batch_size": 8, "model": "vgg16"}, "time_since_restore": 676.0114135742188, "timesteps_since_restore": 0, "iterations_since_restore": 21, "warmup_time": 0.0}
{"loss": 0.7132521409254807, "accuracy": 47.43589743589743, "f1_score": 0.0, "time_this_iter_s": 32.21123027801514, "done": false, "timesteps_total": null, "episodes_total": null, "training_iteration": 22, "trial_id": "757a3_00022", "experiment_id": "f424d4f9f37246a9b46ab407a5b0b6b9", "date": "2022-11-16_22-14-45", "timestamp": 1668626085, "time_total_s": 708.2226438522339, "pid": 20244, "hostname": "DESKTOP-G9R02TV", "node_ip": "127.0.0.1", "config": {"learning_rate": 1e-07, "batch_size": 8, "model": "vgg16"}, "time_since_restore": 708.2226438522339, "timesteps_since_restore": 0, "iterations_since_restore": 22, "warmup_time": 0.0}
{"loss": 0.7076690543411125, "accuracy": 47.43589743589743, "f1_score": 0.0, "time_this_iter_s": 32.38615036010742, "done": false, "timesteps_total": null, "episodes_total": null, "training_iteration": 23, "trial_id": "757a3_00022", "experiment_id": "f424d4f9f37246a9b46ab407a5b0b6b9", "date": "2022-11-16_22-15-17", "timestamp": 1668626117, "time_total_s": 740.6087942123413, "pid": 20244, "hostname": "DESKTOP-G9R02TV", "node_ip": "127.0.0.1", "config": {"learning_rate": 1e-07, "batch_size": 8, "model": "vgg16"}, "time_since_restore": 740.6087942123413, "timesteps_since_restore": 0, "iterations_since_restore": 23, "warmup_time": 0.0}
{"loss": 0.706318847134582, "accuracy": 47.43589743589743, "f1_score": 0.0, "time_this_iter_s": 32.0562059879303, "done": false, "timesteps_total": null, "episodes_total": null, "training_iteration": 24, "trial_id": "757a3_00022", "experiment_id": "f424d4f9f37246a9b46ab407a5b0b6b9", "date": "2022-11-16_22-15-49", "timestamp": 1668626149, "time_total_s": 772.6650002002716, "pid": 20244, "hostname": "DESKTOP-G9R02TV", "node_ip": "127.0.0.1", "config": {"learning_rate": 1e-07, "batch_size": 8, "model": "vgg16"}, "time_since_restore": 772.6650002002716, "timesteps_since_restore": 0, "iterations_since_restore": 24, "warmup_time": 0.0}
{"loss": 0.7063787085378271, "accuracy": 47.43589743589743, "f1_score": 0.0, "time_this_iter_s": 32.39720392227173, "done": false, "timesteps_total": null, "episodes_total": null, "training_iteration": 25, "trial_id": "757a3_00022", "experiment_id": "f424d4f9f37246a9b46ab407a5b0b6b9", "date": "2022-11-16_22-16-21", "timestamp": 1668626181, "time_total_s": 805.0622041225433, "pid": 20244, "hostname": "DESKTOP-G9R02TV", "node_ip": "127.0.0.1", "config": {"learning_rate": 1e-07, "batch_size": 8, "model": "vgg16"}, "time_since_restore": 805.0622041225433, "timesteps_since_restore": 0, "iterations_since_restore": 25, "warmup_time": 0.0}
{"loss": 0.7039326724843082, "accuracy": 47.43589743589743, "f1_score": 0.0, "time_this_iter_s": 31.801735401153564, "done": false, "timesteps_total": null, "episodes_total": null, "training_iteration": 26, "trial_id": "757a3_00022", "experiment_id": "f424d4f9f37246a9b46ab407a5b0b6b9", "date": "2022-11-16_22-16-53", "timestamp": 1668626213, "time_total_s": 836.8639395236969, "pid": 20244, "hostname": "DESKTOP-G9R02TV", "node_ip": "127.0.0.1", "config": {"learning_rate": 1e-07, "batch_size": 8, "model": "vgg16"}, "time_since_restore": 836.8639395236969, "timesteps_since_restore": 0, "iterations_since_restore": 26, "warmup_time": 0.0}
{"loss": 0.7093798645541199, "accuracy": 47.43589743589743, "f1_score": 0.0, "time_this_iter_s": 32.197370767593384, "done": false, "timesteps_total": null, "episodes_total": null, "training_iteration": 27, "trial_id": "757a3_00022", "experiment_id": "f424d4f9f37246a9b46ab407a5b0b6b9", "date": "2022-11-16_22-17-25", "timestamp": 1668626245, "time_total_s": 869.0613102912903, "pid": 20244, "hostname": "DESKTOP-G9R02TV", "node_ip": "127.0.0.1", "config": {"learning_rate": 1e-07, "batch_size": 8, "model": "vgg16"}, "time_since_restore": 869.0613102912903, "timesteps_since_restore": 0, "iterations_since_restore": 27, "warmup_time": 0.0}
{"loss": 0.7042012662969084, "accuracy": 47.43589743589743, "f1_score": 0.0, "time_this_iter_s": 32.415430307388306, "done": false, "timesteps_total": null, "episodes_total": null, "training_iteration": 28, "trial_id": "757a3_00022", "experiment_id": "f424d4f9f37246a9b46ab407a5b0b6b9", "date": "2022-11-16_22-17-58", "timestamp": 1668626278, "time_total_s": 901.4767405986786, "pid": 20244, "hostname": "DESKTOP-G9R02TV", "node_ip": "127.0.0.1", "config": {"learning_rate": 1e-07, "batch_size": 8, "model": "vgg16"}, "time_since_restore": 901.4767405986786, "timesteps_since_restore": 0, "iterations_since_restore": 28, "warmup_time": 0.0}
{"loss": 0.7028106298202124, "accuracy": 47.43589743589743, "f1_score": 0.0, "time_this_iter_s": 32.29005718231201, "done": false, "timesteps_total": null, "episodes_total": null, "training_iteration": 29, "trial_id": "757a3_00022", "experiment_id": "f424d4f9f37246a9b46ab407a5b0b6b9", "date": "2022-11-16_22-18-30", "timestamp": 1668626310, "time_total_s": 933.7667977809906, "pid": 20244, "hostname": "DESKTOP-G9R02TV", "node_ip": "127.0.0.1", "config": {"learning_rate": 1e-07, "batch_size": 8, "model": "vgg16"}, "time_since_restore": 933.7667977809906, "timesteps_since_restore": 0, "iterations_since_restore": 29, "warmup_time": 0.0}
{"loss": 0.7172168829502203, "accuracy": 47.43589743589743, "f1_score": 0.0, "time_this_iter_s": 32.164369106292725, "done": false, "timesteps_total": null, "episodes_total": null, "training_iteration": 30, "trial_id": "757a3_00022", "experiment_id": "f424d4f9f37246a9b46ab407a5b0b6b9", "date": "2022-11-16_22-19-02", "timestamp": 1668626342, "time_total_s": 965.9311668872833, "pid": 20244, "hostname": "DESKTOP-G9R02TV", "node_ip": "127.0.0.1", "config": {"learning_rate": 1e-07, "batch_size": 8, "model": "vgg16"}, "time_since_restore": 965.9311668872833, "timesteps_since_restore": 0, "iterations_since_restore": 30, "warmup_time": 0.0}
