{"loss": 1.490854247003539, "accuracy": 59.82905982905983, "f1_score": 0.6384615384615384, "precision": 0.5971223021582733, "recall": 0.6859504132231405, "time_this_iter_s": 105.7324333190918, "done": false, "timesteps_total": null, "episodes_total": null, "training_iteration": 1, "trial_id": "9ac02_00004", "experiment_id": "565788bb77414257b8ab1496de6c54a2", "date": "2023-01-12_17-59-32", "timestamp": 1673535572, "time_total_s": 105.7324333190918, "pid": 23088, "hostname": "DESKTOP-G9R02TV", "node_ip": "127.0.0.1", "config": {"lr": 0.0005, "batch_size": 4, "epochs": 10, "freeze": false, "model": "resnet152", "with_mlp": false}, "time_since_restore": 105.7324333190918, "timesteps_since_restore": 0, "iterations_since_restore": 1, "warmup_time": 0.0}
{"loss": 0.6460191123505943, "accuracy": 62.39316239316239, "f1_score": 0.6666666666666667, "precision": 0.6153846153846154, "recall": 0.7272727272727273, "time_this_iter_s": 104.78172755241394, "done": false, "timesteps_total": null, "episodes_total": null, "training_iteration": 2, "trial_id": "9ac02_00004", "experiment_id": "565788bb77414257b8ab1496de6c54a2", "date": "2023-01-12_18-01-17", "timestamp": 1673535677, "time_total_s": 210.51416087150574, "pid": 23088, "hostname": "DESKTOP-G9R02TV", "node_ip": "127.0.0.1", "config": {"lr": 0.0005, "batch_size": 4, "epochs": 10, "freeze": false, "model": "resnet152", "with_mlp": false}, "time_since_restore": 210.51416087150574, "timesteps_since_restore": 0, "iterations_since_restore": 2, "warmup_time": 0.0}
{"loss": 1.29594238802918, "accuracy": 54.27350427350427, "f1_score": 0.3184713375796178, "precision": 0.6944444444444444, "recall": 0.2066115702479339, "time_this_iter_s": 103.24380230903625, "done": false, "timesteps_total": null, "episodes_total": null, "training_iteration": 3, "trial_id": "9ac02_00004", "experiment_id": "565788bb77414257b8ab1496de6c54a2", "date": "2023-01-12_18-03-00", "timestamp": 1673535780, "time_total_s": 313.757963180542, "pid": 23088, "hostname": "DESKTOP-G9R02TV", "node_ip": "127.0.0.1", "config": {"lr": 0.0005, "batch_size": 4, "epochs": 10, "freeze": false, "model": "resnet152", "with_mlp": false}, "time_since_restore": 313.757963180542, "timesteps_since_restore": 0, "iterations_since_restore": 3, "warmup_time": 0.0}
{"loss": 0.9898544050689436, "accuracy": 52.13675213675214, "f1_score": 0.2911392405063291, "precision": 0.6216216216216216, "recall": 0.19008264462809918, "time_this_iter_s": 102.4976224899292, "done": false, "timesteps_total": null, "episodes_total": null, "training_iteration": 4, "trial_id": "9ac02_00004", "experiment_id": "565788bb77414257b8ab1496de6c54a2", "date": "2023-01-12_18-04-42", "timestamp": 1673535882, "time_total_s": 416.2555856704712, "pid": 23088, "hostname": "DESKTOP-G9R02TV", "node_ip": "127.0.0.1", "config": {"lr": 0.0005, "batch_size": 4, "epochs": 10, "freeze": false, "model": "resnet152", "with_mlp": false}, "time_since_restore": 416.2555856704712, "timesteps_since_restore": 0, "iterations_since_restore": 4, "warmup_time": 0.0}
{"loss": 0.7898498926407251, "accuracy": 60.68376068376068, "f1_score": 0.5740740740740742, "precision": 0.6526315789473685, "recall": 0.512396694214876, "time_this_iter_s": 102.26362085342407, "done": false, "timesteps_total": null, "episodes_total": null, "training_iteration": 5, "trial_id": "9ac02_00004", "experiment_id": "565788bb77414257b8ab1496de6c54a2", "date": "2023-01-12_18-06-25", "timestamp": 1673535985, "time_total_s": 518.5192065238953, "pid": 23088, "hostname": "DESKTOP-G9R02TV", "node_ip": "127.0.0.1", "config": {"lr": 0.0005, "batch_size": 4, "epochs": 10, "freeze": false, "model": "resnet152", "with_mlp": false}, "time_since_restore": 518.5192065238953, "timesteps_since_restore": 0, "iterations_since_restore": 5, "warmup_time": 0.0}
{"loss": 0.6224045060638689, "accuracy": 61.53846153846154, "f1_score": 0.5588235294117647, "precision": 0.6867469879518072, "recall": 0.47107438016528924, "time_this_iter_s": 102.46909880638123, "done": false, "timesteps_total": null, "episodes_total": null, "training_iteration": 6, "trial_id": "9ac02_00004", "experiment_id": "565788bb77414257b8ab1496de6c54a2", "date": "2023-01-12_18-08-07", "timestamp": 1673536087, "time_total_s": 620.9883053302765, "pid": 23088, "hostname": "DESKTOP-G9R02TV", "node_ip": "127.0.0.1", "config": {"lr": 0.0005, "batch_size": 4, "epochs": 10, "freeze": false, "model": "resnet152", "with_mlp": false}, "time_since_restore": 620.9883053302765, "timesteps_since_restore": 0, "iterations_since_restore": 6, "warmup_time": 0.0}
{"loss": 0.6978816497020233, "accuracy": 61.53846153846154, "f1_score": 0.6086956521739131, "precision": 0.6422018348623854, "recall": 0.5785123966942148, "time_this_iter_s": 102.6139235496521, "done": false, "timesteps_total": null, "episodes_total": null, "training_iteration": 7, "trial_id": "9ac02_00004", "experiment_id": "565788bb77414257b8ab1496de6c54a2", "date": "2023-01-12_18-09-50", "timestamp": 1673536190, "time_total_s": 723.6022288799286, "pid": 23088, "hostname": "DESKTOP-G9R02TV", "node_ip": "127.0.0.1", "config": {"lr": 0.0005, "batch_size": 4, "epochs": 10, "freeze": false, "model": "resnet152", "with_mlp": false}, "time_since_restore": 723.6022288799286, "timesteps_since_restore": 0, "iterations_since_restore": 7, "warmup_time": 0.0}
{"loss": 0.6279802892962073, "accuracy": 66.23931623931624, "f1_score": 0.6183574879227053, "precision": 0.7441860465116279, "recall": 0.5289256198347108, "time_this_iter_s": 102.45278692245483, "done": false, "timesteps_total": null, "episodes_total": null, "training_iteration": 8, "trial_id": "9ac02_00004", "experiment_id": "565788bb77414257b8ab1496de6c54a2", "date": "2023-01-12_18-11-32", "timestamp": 1673536292, "time_total_s": 826.0550158023834, "pid": 23088, "hostname": "DESKTOP-G9R02TV", "node_ip": "127.0.0.1", "config": {"lr": 0.0005, "batch_size": 4, "epochs": 10, "freeze": false, "model": "resnet152", "with_mlp": false}, "time_since_restore": 826.0550158023834, "timesteps_since_restore": 0, "iterations_since_restore": 8, "warmup_time": 0.0}
{"loss": 0.8768521170330863, "accuracy": 63.24786324786324, "f1_score": 0.5473684210526315, "precision": 0.7536231884057971, "recall": 0.4297520661157025, "time_this_iter_s": 102.99014592170715, "done": false, "timesteps_total": null, "episodes_total": null, "training_iteration": 9, "trial_id": "9ac02_00004", "experiment_id": "565788bb77414257b8ab1496de6c54a2", "date": "2023-01-12_18-13-15", "timestamp": 1673536395, "time_total_s": 929.0451617240906, "pid": 23088, "hostname": "DESKTOP-G9R02TV", "node_ip": "127.0.0.1", "config": {"lr": 0.0005, "batch_size": 4, "epochs": 10, "freeze": false, "model": "resnet152", "with_mlp": false}, "time_since_restore": 929.0451617240906, "timesteps_since_restore": 0, "iterations_since_restore": 9, "warmup_time": 0.0}
{"loss": 1.2436228695078793, "accuracy": 59.82905982905983, "f1_score": 0.42682926829268286, "precision": 0.813953488372093, "recall": 0.2892561983471074, "time_this_iter_s": 103.26011562347412, "done": false, "timesteps_total": null, "episodes_total": null, "training_iteration": 10, "trial_id": "9ac02_00004", "experiment_id": "565788bb77414257b8ab1496de6c54a2", "date": "2023-01-12_18-14-59", "timestamp": 1673536499, "time_total_s": 1032.3052773475647, "pid": 23088, "hostname": "DESKTOP-G9R02TV", "node_ip": "127.0.0.1", "config": {"lr": 0.0005, "batch_size": 4, "epochs": 10, "freeze": false, "model": "resnet152", "with_mlp": false}, "time_since_restore": 1032.3052773475647, "timesteps_since_restore": 0, "iterations_since_restore": 10, "warmup_time": 0.0}
