{"loss": 0.6983567588349693, "accuracy": 47.863247863247864, "f1_score": 0.0, "time_this_iter_s": 36.26232600212097, "done": false, "timesteps_total": null, "episodes_total": null, "training_iteration": 1, "trial_id": "bdb12_00010", "experiment_id": "b60121aa50da479ebacb59298b2387ce", "date": "2022-11-14_19-03-16", "timestamp": 1668441796, "time_total_s": 36.26232600212097, "pid": 7188, "hostname": "DESKTOP-G9R02TV", "node_ip": "127.0.0.1", "config": {"learning_rate": 1e-07, "batch_size": 8}, "time_since_restore": 36.26232600212097, "timesteps_since_restore": 0, "iterations_since_restore": 1, "warmup_time": 0.015645503997802734}
{"loss": 0.7112870175614316, "accuracy": 47.863247863247864, "f1_score": 0.0, "time_this_iter_s": 33.44664239883423, "done": false, "timesteps_total": null, "episodes_total": null, "training_iteration": 2, "trial_id": "bdb12_00010", "experiment_id": "b60121aa50da479ebacb59298b2387ce", "date": "2022-11-14_19-03-49", "timestamp": 1668441829, "time_total_s": 69.7089684009552, "pid": 7188, "hostname": "DESKTOP-G9R02TV", "node_ip": "127.0.0.1", "config": {"learning_rate": 1e-07, "batch_size": 8}, "time_since_restore": 69.7089684009552, "timesteps_since_restore": 0, "iterations_since_restore": 2, "warmup_time": 0.015645503997802734}
{"loss": 0.7092005411783854, "accuracy": 47.863247863247864, "f1_score": 0.0, "time_this_iter_s": 33.39976668357849, "done": false, "timesteps_total": null, "episodes_total": null, "training_iteration": 3, "trial_id": "bdb12_00010", "experiment_id": "b60121aa50da479ebacb59298b2387ce", "date": "2022-11-14_19-04-23", "timestamp": 1668441863, "time_total_s": 103.10873508453369, "pid": 7188, "hostname": "DESKTOP-G9R02TV", "node_ip": "127.0.0.1", "config": {"learning_rate": 1e-07, "batch_size": 8}, "time_since_restore": 103.10873508453369, "timesteps_since_restore": 0, "iterations_since_restore": 3, "warmup_time": 0.015645503997802734}
{"loss": 0.7010457617604834, "accuracy": 47.863247863247864, "f1_score": 0.0, "time_this_iter_s": 33.49273991584778, "done": false, "timesteps_total": null, "episodes_total": null, "training_iteration": 4, "trial_id": "bdb12_00010", "experiment_id": "b60121aa50da479ebacb59298b2387ce", "date": "2022-11-14_19-04-56", "timestamp": 1668441896, "time_total_s": 136.60147500038147, "pid": 7188, "hostname": "DESKTOP-G9R02TV", "node_ip": "127.0.0.1", "config": {"learning_rate": 1e-07, "batch_size": 8}, "time_since_restore": 136.60147500038147, "timesteps_since_restore": 0, "iterations_since_restore": 4, "warmup_time": 0.015645503997802734}
{"loss": 0.6994420891134148, "accuracy": 47.863247863247864, "f1_score": 0.0, "time_this_iter_s": 33.15740776062012, "done": false, "timesteps_total": null, "episodes_total": null, "training_iteration": 5, "trial_id": "bdb12_00010", "experiment_id": "b60121aa50da479ebacb59298b2387ce", "date": "2022-11-14_19-05-29", "timestamp": 1668441929, "time_total_s": 169.7588827610016, "pid": 7188, "hostname": "DESKTOP-G9R02TV", "node_ip": "127.0.0.1", "config": {"learning_rate": 1e-07, "batch_size": 8}, "time_since_restore": 169.7588827610016, "timesteps_since_restore": 0, "iterations_since_restore": 5, "warmup_time": 0.015645503997802734}
{"loss": 0.7016948471721421, "accuracy": 47.863247863247864, "f1_score": 0.0, "time_this_iter_s": 33.30465912818909, "done": false, "timesteps_total": null, "episodes_total": null, "training_iteration": 6, "trial_id": "bdb12_00010", "experiment_id": "b60121aa50da479ebacb59298b2387ce", "date": "2022-11-14_19-06-03", "timestamp": 1668441963, "time_total_s": 203.06354188919067, "pid": 7188, "hostname": "DESKTOP-G9R02TV", "node_ip": "127.0.0.1", "config": {"learning_rate": 1e-07, "batch_size": 8}, "time_since_restore": 203.06354188919067, "timesteps_since_restore": 0, "iterations_since_restore": 6, "warmup_time": 0.015645503997802734}
{"loss": 0.7054872431306758, "accuracy": 47.863247863247864, "f1_score": 0.0, "time_this_iter_s": 33.43035626411438, "done": false, "timesteps_total": null, "episodes_total": null, "training_iteration": 7, "trial_id": "bdb12_00010", "experiment_id": "b60121aa50da479ebacb59298b2387ce", "date": "2022-11-14_19-06-36", "timestamp": 1668441996, "time_total_s": 236.49389815330505, "pid": 7188, "hostname": "DESKTOP-G9R02TV", "node_ip": "127.0.0.1", "config": {"learning_rate": 1e-07, "batch_size": 8}, "time_since_restore": 236.49389815330505, "timesteps_since_restore": 0, "iterations_since_restore": 7, "warmup_time": 0.015645503997802734}
{"loss": 0.7043524848090278, "accuracy": 47.863247863247864, "f1_score": 0.0, "time_this_iter_s": 33.180291414260864, "done": false, "timesteps_total": null, "episodes_total": null, "training_iteration": 8, "trial_id": "bdb12_00010", "experiment_id": "b60121aa50da479ebacb59298b2387ce", "date": "2022-11-14_19-07-09", "timestamp": 1668442029, "time_total_s": 269.6741895675659, "pid": 7188, "hostname": "DESKTOP-G9R02TV", "node_ip": "127.0.0.1", "config": {"learning_rate": 1e-07, "batch_size": 8}, "time_since_restore": 269.6741895675659, "timesteps_since_restore": 0, "iterations_since_restore": 8, "warmup_time": 0.015645503997802734}
{"loss": 0.7009662725986578, "accuracy": 47.863247863247864, "f1_score": 0.0, "time_this_iter_s": 33.39537215232849, "done": false, "timesteps_total": null, "episodes_total": null, "training_iteration": 9, "trial_id": "bdb12_00010", "experiment_id": "b60121aa50da479ebacb59298b2387ce", "date": "2022-11-14_19-07-43", "timestamp": 1668442063, "time_total_s": 303.0695617198944, "pid": 7188, "hostname": "DESKTOP-G9R02TV", "node_ip": "127.0.0.1", "config": {"learning_rate": 1e-07, "batch_size": 8}, "time_since_restore": 303.0695617198944, "timesteps_since_restore": 0, "iterations_since_restore": 9, "warmup_time": 0.015645503997802734}
{"loss": 0.7053636730226696, "accuracy": 47.863247863247864, "f1_score": 0.0, "time_this_iter_s": 33.35205841064453, "done": false, "timesteps_total": null, "episodes_total": null, "training_iteration": 10, "trial_id": "bdb12_00010", "experiment_id": "b60121aa50da479ebacb59298b2387ce", "date": "2022-11-14_19-08-16", "timestamp": 1668442096, "time_total_s": 336.42162013053894, "pid": 7188, "hostname": "DESKTOP-G9R02TV", "node_ip": "127.0.0.1", "config": {"learning_rate": 1e-07, "batch_size": 8}, "time_since_restore": 336.42162013053894, "timesteps_since_restore": 0, "iterations_since_restore": 10, "warmup_time": 0.015645503997802734}
{"loss": 0.7084362323467548, "accuracy": 47.863247863247864, "f1_score": 0.0, "time_this_iter_s": 32.94592237472534, "done": false, "timesteps_total": null, "episodes_total": null, "training_iteration": 11, "trial_id": "bdb12_00010", "experiment_id": "b60121aa50da479ebacb59298b2387ce", "date": "2022-11-14_19-08-49", "timestamp": 1668442129, "time_total_s": 369.3675425052643, "pid": 7188, "hostname": "DESKTOP-G9R02TV", "node_ip": "127.0.0.1", "config": {"learning_rate": 1e-07, "batch_size": 8}, "time_since_restore": 369.3675425052643, "timesteps_since_restore": 0, "iterations_since_restore": 11, "warmup_time": 0.015645503997802734}
{"loss": 0.7024363330286792, "accuracy": 47.863247863247864, "f1_score": 0.0, "time_this_iter_s": 33.381712436676025, "done": false, "timesteps_total": null, "episodes_total": null, "training_iteration": 12, "trial_id": "bdb12_00010", "experiment_id": "b60121aa50da479ebacb59298b2387ce", "date": "2022-11-14_19-09-22", "timestamp": 1668442162, "time_total_s": 402.7492549419403, "pid": 7188, "hostname": "DESKTOP-G9R02TV", "node_ip": "127.0.0.1", "config": {"learning_rate": 1e-07, "batch_size": 8}, "time_since_restore": 402.7492549419403, "timesteps_since_restore": 0, "iterations_since_restore": 12, "warmup_time": 0.015645503997802734}
{"loss": 0.703762934758113, "accuracy": 47.863247863247864, "f1_score": 0.0, "time_this_iter_s": 33.04043769836426, "done": false, "timesteps_total": null, "episodes_total": null, "training_iteration": 13, "trial_id": "bdb12_00010", "experiment_id": "b60121aa50da479ebacb59298b2387ce", "date": "2022-11-14_19-09-55", "timestamp": 1668442195, "time_total_s": 435.78969264030457, "pid": 7188, "hostname": "DESKTOP-G9R02TV", "node_ip": "127.0.0.1", "config": {"learning_rate": 1e-07, "batch_size": 8}, "time_since_restore": 435.78969264030457, "timesteps_since_restore": 0, "iterations_since_restore": 13, "warmup_time": 0.015645503997802734}
{"loss": 0.7096267439361311, "accuracy": 47.863247863247864, "f1_score": 0.0, "time_this_iter_s": 32.85241508483887, "done": false, "timesteps_total": null, "episodes_total": null, "training_iteration": 14, "trial_id": "bdb12_00010", "experiment_id": "b60121aa50da479ebacb59298b2387ce", "date": "2022-11-14_19-10-28", "timestamp": 1668442228, "time_total_s": 468.64210772514343, "pid": 7188, "hostname": "DESKTOP-G9R02TV", "node_ip": "127.0.0.1", "config": {"learning_rate": 1e-07, "batch_size": 8}, "time_since_restore": 468.64210772514343, "timesteps_since_restore": 0, "iterations_since_restore": 14, "warmup_time": 0.015645503997802734}
{"loss": 0.6950748802250267, "accuracy": 47.863247863247864, "f1_score": 0.0, "time_this_iter_s": 32.985252380371094, "done": false, "timesteps_total": null, "episodes_total": null, "training_iteration": 15, "trial_id": "bdb12_00010", "experiment_id": "b60121aa50da479ebacb59298b2387ce", "date": "2022-11-14_19-11-01", "timestamp": 1668442261, "time_total_s": 501.6273601055145, "pid": 7188, "hostname": "DESKTOP-G9R02TV", "node_ip": "127.0.0.1", "config": {"learning_rate": 1e-07, "batch_size": 8}, "time_since_restore": 501.6273601055145, "timesteps_since_restore": 0, "iterations_since_restore": 15, "warmup_time": 0.015645503997802734}
{"loss": 0.700548090486445, "accuracy": 47.863247863247864, "f1_score": 0.0, "time_this_iter_s": 33.08157753944397, "done": false, "timesteps_total": null, "episodes_total": null, "training_iteration": 16, "trial_id": "bdb12_00010", "experiment_id": "b60121aa50da479ebacb59298b2387ce", "date": "2022-11-14_19-11-34", "timestamp": 1668442294, "time_total_s": 534.7089376449585, "pid": 7188, "hostname": "DESKTOP-G9R02TV", "node_ip": "127.0.0.1", "config": {"learning_rate": 1e-07, "batch_size": 8}, "time_since_restore": 534.7089376449585, "timesteps_since_restore": 0, "iterations_since_restore": 16, "warmup_time": 0.015645503997802734}
{"loss": 0.6980080237755408, "accuracy": 47.863247863247864, "f1_score": 0.0, "time_this_iter_s": 32.695430278778076, "done": false, "timesteps_total": null, "episodes_total": null, "training_iteration": 17, "trial_id": "bdb12_00010", "experiment_id": "b60121aa50da479ebacb59298b2387ce", "date": "2022-11-14_19-12-07", "timestamp": 1668442327, "time_total_s": 567.4043679237366, "pid": 7188, "hostname": "DESKTOP-G9R02TV", "node_ip": "127.0.0.1", "config": {"learning_rate": 1e-07, "batch_size": 8}, "time_since_restore": 567.4043679237366, "timesteps_since_restore": 0, "iterations_since_restore": 17, "warmup_time": 0.015645503997802734}
{"loss": 0.7002840612688636, "accuracy": 47.863247863247864, "f1_score": 0.0, "time_this_iter_s": 33.11706018447876, "done": false, "timesteps_total": null, "episodes_total": null, "training_iteration": 18, "trial_id": "bdb12_00010", "experiment_id": "b60121aa50da479ebacb59298b2387ce", "date": "2022-11-14_19-12-40", "timestamp": 1668442360, "time_total_s": 600.5214281082153, "pid": 7188, "hostname": "DESKTOP-G9R02TV", "node_ip": "127.0.0.1", "config": {"learning_rate": 1e-07, "batch_size": 8}, "time_since_restore": 600.5214281082153, "timesteps_since_restore": 0, "iterations_since_restore": 18, "warmup_time": 0.015645503997802734}
{"loss": 0.7110036866277711, "accuracy": 47.863247863247864, "f1_score": 0.0, "time_this_iter_s": 33.30713367462158, "done": false, "timesteps_total": null, "episodes_total": null, "training_iteration": 19, "trial_id": "bdb12_00010", "experiment_id": "b60121aa50da479ebacb59298b2387ce", "date": "2022-11-14_19-13-13", "timestamp": 1668442393, "time_total_s": 633.8285617828369, "pid": 7188, "hostname": "DESKTOP-G9R02TV", "node_ip": "127.0.0.1", "config": {"learning_rate": 1e-07, "batch_size": 8}, "time_since_restore": 633.8285617828369, "timesteps_since_restore": 0, "iterations_since_restore": 19, "warmup_time": 0.015645503997802734}
{"loss": 0.7139245057717348, "accuracy": 47.863247863247864, "f1_score": 0.0, "time_this_iter_s": 32.93251824378967, "done": false, "timesteps_total": null, "episodes_total": null, "training_iteration": 20, "trial_id": "bdb12_00010", "experiment_id": "b60121aa50da479ebacb59298b2387ce", "date": "2022-11-14_19-13-46", "timestamp": 1668442426, "time_total_s": 666.7610800266266, "pid": 7188, "hostname": "DESKTOP-G9R02TV", "node_ip": "127.0.0.1", "config": {"learning_rate": 1e-07, "batch_size": 8}, "time_since_restore": 666.7610800266266, "timesteps_since_restore": 0, "iterations_since_restore": 20, "warmup_time": 0.015645503997802734}
{"loss": 0.7030177972255609, "accuracy": 47.863247863247864, "f1_score": 0.0, "time_this_iter_s": 32.8376350402832, "done": false, "timesteps_total": null, "episodes_total": null, "training_iteration": 21, "trial_id": "bdb12_00010", "experiment_id": "b60121aa50da479ebacb59298b2387ce", "date": "2022-11-14_19-14-19", "timestamp": 1668442459, "time_total_s": 699.5987150669098, "pid": 7188, "hostname": "DESKTOP-G9R02TV", "node_ip": "127.0.0.1", "config": {"learning_rate": 1e-07, "batch_size": 8}, "time_since_restore": 699.5987150669098, "timesteps_since_restore": 0, "iterations_since_restore": 21, "warmup_time": 0.015645503997802734}
{"loss": 0.6966042151817908, "accuracy": 47.863247863247864, "f1_score": 0.0, "time_this_iter_s": 33.09642767906189, "done": false, "timesteps_total": null, "episodes_total": null, "training_iteration": 22, "trial_id": "bdb12_00010", "experiment_id": "b60121aa50da479ebacb59298b2387ce", "date": "2022-11-14_19-14-52", "timestamp": 1668442492, "time_total_s": 732.6951427459717, "pid": 7188, "hostname": "DESKTOP-G9R02TV", "node_ip": "127.0.0.1", "config": {"learning_rate": 1e-07, "batch_size": 8}, "time_since_restore": 732.6951427459717, "timesteps_since_restore": 0, "iterations_since_restore": 22, "warmup_time": 0.015645503997802734}
{"loss": 0.7101022443200788, "accuracy": 47.863247863247864, "f1_score": 0.0, "time_this_iter_s": 33.20486283302307, "done": false, "timesteps_total": null, "episodes_total": null, "training_iteration": 23, "trial_id": "bdb12_00010", "experiment_id": "b60121aa50da479ebacb59298b2387ce", "date": "2022-11-14_19-15-26", "timestamp": 1668442526, "time_total_s": 765.9000055789948, "pid": 7188, "hostname": "DESKTOP-G9R02TV", "node_ip": "127.0.0.1", "config": {"learning_rate": 1e-07, "batch_size": 8}, "time_since_restore": 765.9000055789948, "timesteps_since_restore": 0, "iterations_since_restore": 23, "warmup_time": 0.015645503997802734}
{"loss": 0.7142415495000334, "accuracy": 47.863247863247864, "f1_score": 0.0, "time_this_iter_s": 33.0708110332489, "done": false, "timesteps_total": null, "episodes_total": null, "training_iteration": 24, "trial_id": "bdb12_00010", "experiment_id": "b60121aa50da479ebacb59298b2387ce", "date": "2022-11-14_19-15-59", "timestamp": 1668442559, "time_total_s": 798.9708166122437, "pid": 7188, "hostname": "DESKTOP-G9R02TV", "node_ip": "127.0.0.1", "config": {"learning_rate": 1e-07, "batch_size": 8}, "time_since_restore": 798.9708166122437, "timesteps_since_restore": 0, "iterations_since_restore": 24, "warmup_time": 0.015645503997802734}
{"loss": 0.6995536608573718, "accuracy": 47.863247863247864, "f1_score": 0.0, "time_this_iter_s": 32.91415596008301, "done": false, "timesteps_total": null, "episodes_total": null, "training_iteration": 25, "trial_id": "bdb12_00010", "experiment_id": "b60121aa50da479ebacb59298b2387ce", "date": "2022-11-14_19-16-31", "timestamp": 1668442591, "time_total_s": 831.8849725723267, "pid": 7188, "hostname": "DESKTOP-G9R02TV", "node_ip": "127.0.0.1", "config": {"learning_rate": 1e-07, "batch_size": 8}, "time_since_restore": 831.8849725723267, "timesteps_since_restore": 0, "iterations_since_restore": 25, "warmup_time": 0.015645503997802734}
{"loss": 0.7072449382553753, "accuracy": 47.863247863247864, "f1_score": 0.0, "time_this_iter_s": 32.88289141654968, "done": false, "timesteps_total": null, "episodes_total": null, "training_iteration": 26, "trial_id": "bdb12_00010", "experiment_id": "b60121aa50da479ebacb59298b2387ce", "date": "2022-11-14_19-17-04", "timestamp": 1668442624, "time_total_s": 864.7678639888763, "pid": 7188, "hostname": "DESKTOP-G9R02TV", "node_ip": "127.0.0.1", "config": {"learning_rate": 1e-07, "batch_size": 8}, "time_since_restore": 864.7678639888763, "timesteps_since_restore": 0, "iterations_since_restore": 26, "warmup_time": 0.015645503997802734}
{"loss": 0.7017852913620125, "accuracy": 47.863247863247864, "f1_score": 0.0, "time_this_iter_s": 32.893332719802856, "done": false, "timesteps_total": null, "episodes_total": null, "training_iteration": 27, "trial_id": "bdb12_00010", "experiment_id": "b60121aa50da479ebacb59298b2387ce", "date": "2022-11-14_19-17-37", "timestamp": 1668442657, "time_total_s": 897.6611967086792, "pid": 7188, "hostname": "DESKTOP-G9R02TV", "node_ip": "127.0.0.1", "config": {"learning_rate": 1e-07, "batch_size": 8}, "time_since_restore": 897.6611967086792, "timesteps_since_restore": 0, "iterations_since_restore": 27, "warmup_time": 0.015645503997802734}
{"loss": 0.71363524086455, "accuracy": 47.863247863247864, "f1_score": 0.0, "time_this_iter_s": 32.929715394973755, "done": false, "timesteps_total": null, "episodes_total": null, "training_iteration": 28, "trial_id": "bdb12_00010", "experiment_id": "b60121aa50da479ebacb59298b2387ce", "date": "2022-11-14_19-18-10", "timestamp": 1668442690, "time_total_s": 930.590912103653, "pid": 7188, "hostname": "DESKTOP-G9R02TV", "node_ip": "127.0.0.1", "config": {"learning_rate": 1e-07, "batch_size": 8}, "time_since_restore": 930.590912103653, "timesteps_since_restore": 0, "iterations_since_restore": 28, "warmup_time": 0.015645503997802734}
{"loss": 0.7063180646325788, "accuracy": 47.863247863247864, "f1_score": 0.0, "time_this_iter_s": 33.13285708427429, "done": false, "timesteps_total": null, "episodes_total": null, "training_iteration": 29, "trial_id": "bdb12_00010", "experiment_id": "b60121aa50da479ebacb59298b2387ce", "date": "2022-11-14_19-18-43", "timestamp": 1668442723, "time_total_s": 963.7237691879272, "pid": 7188, "hostname": "DESKTOP-G9R02TV", "node_ip": "127.0.0.1", "config": {"learning_rate": 1e-07, "batch_size": 8}, "time_since_restore": 963.7237691879272, "timesteps_since_restore": 0, "iterations_since_restore": 29, "warmup_time": 0.015645503997802734}
{"loss": 0.6997123131385217, "accuracy": 47.863247863247864, "f1_score": 0.0, "time_this_iter_s": 33.03124165534973, "done": false, "timesteps_total": null, "episodes_total": null, "training_iteration": 30, "trial_id": "bdb12_00010", "experiment_id": "b60121aa50da479ebacb59298b2387ce", "date": "2022-11-14_19-19-16", "timestamp": 1668442756, "time_total_s": 996.755010843277, "pid": 7188, "hostname": "DESKTOP-G9R02TV", "node_ip": "127.0.0.1", "config": {"learning_rate": 1e-07, "batch_size": 8}, "time_since_restore": 996.755010843277, "timesteps_since_restore": 0, "iterations_since_restore": 30, "warmup_time": 0.015645503997802734}
