{"loss": 753.1515758547008, "accuracy": 49.14529914529914, "f1_score": 0.5608856088560885, "precision": 0.5241379310344828, "recall": 0.6031746031746031, "time_this_iter_s": 89.94221353530884, "done": false, "timesteps_total": null, "episodes_total": null, "training_iteration": 1, "trial_id": "6ba6d_00000", "experiment_id": "26be2a7fa128410fa3a8e01dae114301", "date": "2022-11-29_17-39-33", "timestamp": 1669732773, "time_total_s": 89.94221353530884, "pid": 19740, "hostname": "DESKTOP-G9R02TV", "node_ip": "127.0.0.1", "config": {"learning_rate": 0.01, "batch_size": 2, "model": "inception_v3", "epochs": 20}, "time_since_restore": 89.94221353530884, "timesteps_since_restore": 0, "iterations_since_restore": 1, "warmup_time": 0.0}
{"loss": 18.473382411858974, "accuracy": 49.572649572649574, "f1_score": 0.46846846846846846, "precision": 0.5416666666666666, "recall": 0.4126984126984127, "time_this_iter_s": 87.42256355285645, "done": false, "timesteps_total": null, "episodes_total": null, "training_iteration": 2, "trial_id": "6ba6d_00000", "experiment_id": "26be2a7fa128410fa3a8e01dae114301", "date": "2022-11-29_17-41-00", "timestamp": 1669732860, "time_total_s": 177.36477708816528, "pid": 19740, "hostname": "DESKTOP-G9R02TV", "node_ip": "127.0.0.1", "config": {"learning_rate": 0.01, "batch_size": 2, "model": "inception_v3", "epochs": 20}, "time_since_restore": 177.36477708816528, "timesteps_since_restore": 0, "iterations_since_restore": 2, "warmup_time": 0.0}
{"loss": 2.011218470385951, "accuracy": 42.73504273504273, "f1_score": 0.22093023255813954, "precision": 0.41304347826086957, "recall": 0.15079365079365079, "time_this_iter_s": 87.34322738647461, "done": false, "timesteps_total": null, "episodes_total": null, "training_iteration": 3, "trial_id": "6ba6d_00000", "experiment_id": "26be2a7fa128410fa3a8e01dae114301", "date": "2022-11-29_17-42-28", "timestamp": 1669732948, "time_total_s": 264.7080044746399, "pid": 19740, "hostname": "DESKTOP-G9R02TV", "node_ip": "127.0.0.1", "config": {"learning_rate": 0.01, "batch_size": 2, "model": "inception_v3", "epochs": 20}, "time_since_restore": 264.7080044746399, "timesteps_since_restore": 0, "iterations_since_restore": 3, "warmup_time": 0.0}
{"loss": 2.6528075128538995, "accuracy": 46.58119658119658, "f1_score": 0.4292237442922375, "precision": 0.5053763440860215, "recall": 0.373015873015873, "time_this_iter_s": 88.25310826301575, "done": false, "timesteps_total": null, "episodes_total": null, "training_iteration": 4, "trial_id": "6ba6d_00000", "experiment_id": "26be2a7fa128410fa3a8e01dae114301", "date": "2022-11-29_17-43-56", "timestamp": 1669733036, "time_total_s": 352.96111273765564, "pid": 19740, "hostname": "DESKTOP-G9R02TV", "node_ip": "127.0.0.1", "config": {"learning_rate": 0.01, "batch_size": 2, "model": "inception_v3", "epochs": 20}, "time_since_restore": 352.96111273765564, "timesteps_since_restore": 0, "iterations_since_restore": 4, "warmup_time": 0.0}
{"loss": 0.8330511761526777, "accuracy": 52.991452991452995, "f1_score": 0.45544554455445546, "precision": 0.6052631578947368, "recall": 0.36507936507936506, "time_this_iter_s": 87.01775979995728, "done": false, "timesteps_total": null, "episodes_total": null, "training_iteration": 5, "trial_id": "6ba6d_00000", "experiment_id": "26be2a7fa128410fa3a8e01dae114301", "date": "2022-11-29_17-45-23", "timestamp": 1669733123, "time_total_s": 439.9788725376129, "pid": 19740, "hostname": "DESKTOP-G9R02TV", "node_ip": "127.0.0.1", "config": {"learning_rate": 0.01, "batch_size": 2, "model": "inception_v3", "epochs": 20}, "time_since_restore": 439.9788725376129, "timesteps_since_restore": 0, "iterations_since_restore": 5, "warmup_time": 0.0}
{"loss": 1.306259285690438, "accuracy": 53.84615384615385, "f1_score": 0.34146341463414637, "precision": 0.7368421052631579, "recall": 0.2222222222222222, "time_this_iter_s": 87.97920680046082, "done": false, "timesteps_total": null, "episodes_total": null, "training_iteration": 6, "trial_id": "6ba6d_00000", "experiment_id": "26be2a7fa128410fa3a8e01dae114301", "date": "2022-11-29_17-46-51", "timestamp": 1669733211, "time_total_s": 527.9580793380737, "pid": 19740, "hostname": "DESKTOP-G9R02TV", "node_ip": "127.0.0.1", "config": {"learning_rate": 0.01, "batch_size": 2, "model": "inception_v3", "epochs": 20}, "time_since_restore": 527.9580793380737, "timesteps_since_restore": 0, "iterations_since_restore": 6, "warmup_time": 0.0}
{"loss": 1.1122474344367654, "accuracy": 46.15384615384615, "f1_score": 0.0, "precision": 1.0, "recall": 0.0, "time_this_iter_s": 86.60076379776001, "done": false, "timesteps_total": null, "episodes_total": null, "training_iteration": 7, "trial_id": "6ba6d_00000", "experiment_id": "26be2a7fa128410fa3a8e01dae114301", "date": "2022-11-29_17-48-18", "timestamp": 1669733298, "time_total_s": 614.5588431358337, "pid": 19740, "hostname": "DESKTOP-G9R02TV", "node_ip": "127.0.0.1", "config": {"learning_rate": 0.01, "batch_size": 2, "model": "inception_v3", "epochs": 20}, "time_since_restore": 614.5588431358337, "timesteps_since_restore": 0, "iterations_since_restore": 7, "warmup_time": 0.0}
{"loss": 1.6749491895365918, "accuracy": 44.01709401709402, "f1_score": 0.2514285714285714, "precision": 0.4489795918367347, "recall": 0.1746031746031746, "time_this_iter_s": 87.37329149246216, "done": false, "timesteps_total": null, "episodes_total": null, "training_iteration": 8, "trial_id": "6ba6d_00000", "experiment_id": "26be2a7fa128410fa3a8e01dae114301", "date": "2022-11-29_17-49-45", "timestamp": 1669733385, "time_total_s": 701.9321346282959, "pid": 19740, "hostname": "DESKTOP-G9R02TV", "node_ip": "127.0.0.1", "config": {"learning_rate": 0.01, "batch_size": 2, "model": "inception_v3", "epochs": 20}, "time_since_restore": 701.9321346282959, "timesteps_since_restore": 0, "iterations_since_restore": 8, "warmup_time": 0.0}
{"loss": 1.002042982313368, "accuracy": 46.58119658119658, "f1_score": 0.1935483870967742, "precision": 0.5172413793103449, "recall": 0.11904761904761904, "time_this_iter_s": 87.59256029129028, "done": false, "timesteps_total": null, "episodes_total": null, "training_iteration": 9, "trial_id": "6ba6d_00000", "experiment_id": "26be2a7fa128410fa3a8e01dae114301", "date": "2022-11-29_17-51-13", "timestamp": 1669733473, "time_total_s": 789.5246949195862, "pid": 19740, "hostname": "DESKTOP-G9R02TV", "node_ip": "127.0.0.1", "config": {"learning_rate": 0.01, "batch_size": 2, "model": "inception_v3", "epochs": 20}, "time_since_restore": 789.5246949195862, "timesteps_since_restore": 0, "iterations_since_restore": 9, "warmup_time": 0.0}
{"loss": 1.0002640292175815, "accuracy": 46.15384615384615, "f1_score": 0.0, "precision": 1.0, "recall": 0.0, "time_this_iter_s": 86.95299029350281, "done": false, "timesteps_total": null, "episodes_total": null, "training_iteration": 10, "trial_id": "6ba6d_00000", "experiment_id": "26be2a7fa128410fa3a8e01dae114301", "date": "2022-11-29_17-52-39", "timestamp": 1669733559, "time_total_s": 876.477685213089, "pid": 19740, "hostname": "DESKTOP-G9R02TV", "node_ip": "127.0.0.1", "config": {"learning_rate": 0.01, "batch_size": 2, "model": "inception_v3", "epochs": 20}, "time_since_restore": 876.477685213089, "timesteps_since_restore": 0, "iterations_since_restore": 10, "warmup_time": 0.0}
{"loss": 1.0555276463174412, "accuracy": 54.27350427350427, "f1_score": 0.4088397790055249, "precision": 0.6727272727272727, "recall": 0.29365079365079366, "time_this_iter_s": 87.08003807067871, "done": false, "timesteps_total": null, "episodes_total": null, "training_iteration": 11, "trial_id": "6ba6d_00000", "experiment_id": "26be2a7fa128410fa3a8e01dae114301", "date": "2022-11-29_17-54-07", "timestamp": 1669733647, "time_total_s": 963.5577232837677, "pid": 19740, "hostname": "DESKTOP-G9R02TV", "node_ip": "127.0.0.1", "config": {"learning_rate": 0.01, "batch_size": 2, "model": "inception_v3", "epochs": 20}, "time_since_restore": 963.5577232837677, "timesteps_since_restore": 0, "iterations_since_restore": 11, "warmup_time": 0.0}
{"loss": 0.9157317071898371, "accuracy": 54.700854700854705, "f1_score": 0.369047619047619, "precision": 0.7380952380952381, "recall": 0.24603174603174602, "time_this_iter_s": 86.93511962890625, "done": false, "timesteps_total": null, "episodes_total": null, "training_iteration": 12, "trial_id": "6ba6d_00000", "experiment_id": "26be2a7fa128410fa3a8e01dae114301", "date": "2022-11-29_17-55-33", "timestamp": 1669733733, "time_total_s": 1050.492842912674, "pid": 19740, "hostname": "DESKTOP-G9R02TV", "node_ip": "127.0.0.1", "config": {"learning_rate": 0.01, "batch_size": 2, "model": "inception_v3", "epochs": 20}, "time_since_restore": 1050.492842912674, "timesteps_since_restore": 0, "iterations_since_restore": 12, "warmup_time": 0.0}
{"loss": 0.7614309848883213, "accuracy": 46.58119658119658, "f1_score": 0.015748031496062992, "precision": 1.0, "recall": 0.007936507936507936, "time_this_iter_s": 88.05483317375183, "done": false, "timesteps_total": null, "episodes_total": null, "training_iteration": 13, "trial_id": "6ba6d_00000", "experiment_id": "26be2a7fa128410fa3a8e01dae114301", "date": "2022-11-29_17-57-02", "timestamp": 1669733822, "time_total_s": 1138.5476760864258, "pid": 19740, "hostname": "DESKTOP-G9R02TV", "node_ip": "127.0.0.1", "config": {"learning_rate": 0.01, "batch_size": 2, "model": "inception_v3", "epochs": 20}, "time_since_restore": 1138.5476760864258, "timesteps_since_restore": 0, "iterations_since_restore": 13, "warmup_time": 0.0}
{"loss": 0.7405810885959201, "accuracy": 50.85470085470085, "f1_score": 0.22818791946308725, "precision": 0.7391304347826086, "recall": 0.1349206349206349, "time_this_iter_s": 87.8417341709137, "done": false, "timesteps_total": null, "episodes_total": null, "training_iteration": 14, "trial_id": "6ba6d_00000", "experiment_id": "26be2a7fa128410fa3a8e01dae114301", "date": "2022-11-29_17-58-29", "timestamp": 1669733909, "time_total_s": 1226.3894102573395, "pid": 19740, "hostname": "DESKTOP-G9R02TV", "node_ip": "127.0.0.1", "config": {"learning_rate": 0.01, "batch_size": 2, "model": "inception_v3", "epochs": 20}, "time_since_restore": 1226.3894102573395, "timesteps_since_restore": 0, "iterations_since_restore": 14, "warmup_time": 0.0}
{"loss": 2.6164806398571048, "accuracy": 54.27350427350427, "f1_score": 0.45128205128205123, "precision": 0.6376811594202898, "recall": 0.3492063492063492, "time_this_iter_s": 85.1344666481018, "done": false, "timesteps_total": null, "episodes_total": null, "training_iteration": 15, "trial_id": "6ba6d_00000", "experiment_id": "26be2a7fa128410fa3a8e01dae114301", "date": "2022-11-29_17-59-55", "timestamp": 1669733995, "time_total_s": 1311.5238769054413, "pid": 19740, "hostname": "DESKTOP-G9R02TV", "node_ip": "127.0.0.1", "config": {"learning_rate": 0.01, "batch_size": 2, "model": "inception_v3", "epochs": 20}, "time_since_restore": 1311.5238769054413, "timesteps_since_restore": 0, "iterations_since_restore": 15, "warmup_time": 0.0}
{"loss": 7.521981002938034, "accuracy": 47.008547008547005, "f1_score": 0.3861386138613862, "precision": 0.5131578947368421, "recall": 0.30952380952380953, "time_this_iter_s": 85.1614465713501, "done": false, "timesteps_total": null, "episodes_total": null, "training_iteration": 16, "trial_id": "6ba6d_00000", "experiment_id": "26be2a7fa128410fa3a8e01dae114301", "date": "2022-11-29_18-01-20", "timestamp": 1669734080, "time_total_s": 1396.6853234767914, "pid": 19740, "hostname": "DESKTOP-G9R02TV", "node_ip": "127.0.0.1", "config": {"learning_rate": 0.01, "batch_size": 2, "model": "inception_v3", "epochs": 20}, "time_since_restore": 1396.6853234767914, "timesteps_since_restore": 0, "iterations_since_restore": 16, "warmup_time": 0.0}
{"loss": 7.592335758046207, "accuracy": 46.15384615384615, "f1_score": 0.0, "precision": 1.0, "recall": 0.0, "time_this_iter_s": 88.34854030609131, "done": false, "timesteps_total": null, "episodes_total": null, "training_iteration": 17, "trial_id": "6ba6d_00000", "experiment_id": "26be2a7fa128410fa3a8e01dae114301", "date": "2022-11-29_18-02-48", "timestamp": 1669734168, "time_total_s": 1485.0338637828827, "pid": 19740, "hostname": "DESKTOP-G9R02TV", "node_ip": "127.0.0.1", "config": {"learning_rate": 0.01, "batch_size": 2, "model": "inception_v3", "epochs": 20}, "time_since_restore": 1485.0338637828827, "timesteps_since_restore": 0, "iterations_since_restore": 17, "warmup_time": 0.0}
{"loss": 0.9079305534688835, "accuracy": 47.863247863247864, "f1_score": 0.29069767441860467, "precision": 0.5434782608695652, "recall": 0.1984126984126984, "time_this_iter_s": 87.18877172470093, "done": false, "timesteps_total": null, "episodes_total": null, "training_iteration": 18, "trial_id": "6ba6d_00000", "experiment_id": "26be2a7fa128410fa3a8e01dae114301", "date": "2022-11-29_18-04-15", "timestamp": 1669734255, "time_total_s": 1572.2226355075836, "pid": 19740, "hostname": "DESKTOP-G9R02TV", "node_ip": "127.0.0.1", "config": {"learning_rate": 0.01, "batch_size": 2, "model": "inception_v3", "epochs": 20}, "time_since_restore": 1572.2226355075836, "timesteps_since_restore": 0, "iterations_since_restore": 18, "warmup_time": 0.0}
{"loss": 0.6848087799854767, "accuracy": 47.863247863247864, "f1_score": 0.07575757575757576, "precision": 0.8333333333333334, "recall": 0.03968253968253968, "time_this_iter_s": 87.88395762443542, "done": false, "timesteps_total": null, "episodes_total": null, "training_iteration": 19, "trial_id": "6ba6d_00000", "experiment_id": "26be2a7fa128410fa3a8e01dae114301", "date": "2022-11-29_18-05-43", "timestamp": 1669734343, "time_total_s": 1660.106593132019, "pid": 19740, "hostname": "DESKTOP-G9R02TV", "node_ip": "127.0.0.1", "config": {"learning_rate": 0.01, "batch_size": 2, "model": "inception_v3", "epochs": 20}, "time_since_restore": 1660.106593132019, "timesteps_since_restore": 0, "iterations_since_restore": 19, "warmup_time": 0.0}
{"loss": 0.9218341142703326, "accuracy": 52.991452991452995, "f1_score": 0.5089285714285714, "precision": 0.5816326530612245, "recall": 0.4523809523809524, "time_this_iter_s": 88.03787398338318, "done": false, "timesteps_total": null, "episodes_total": null, "training_iteration": 20, "trial_id": "6ba6d_00000", "experiment_id": "26be2a7fa128410fa3a8e01dae114301", "date": "2022-11-29_18-07-11", "timestamp": 1669734431, "time_total_s": 1748.1444671154022, "pid": 19740, "hostname": "DESKTOP-G9R02TV", "node_ip": "127.0.0.1", "config": {"learning_rate": 0.01, "batch_size": 2, "model": "inception_v3", "epochs": 20}, "time_since_restore": 1748.1444671154022, "timesteps_since_restore": 0, "iterations_since_restore": 20, "warmup_time": 0.0}
